pyuegc/__init__.py
pyuegc/_unicode.py
pyuegc/_version.py
pyuegc/egc.py
pyuegc-16.0.3.dist-info/LICENSE
pyuegc-16.0.3.dist-info/METADATA
pyuegc-16.0.3.dist-info/WHEEL
pyuegc-16.0.3.dist-info/top_level.txt
pyuegc-16.0.3.dist-info/RECORD
