Metadata-Version: 2.2
Name: pyuegc
Version: 16.0.3
Summary: An implementation of the Unicode algorithm for breaking code point sequences into extended grapheme clusters as specified in UAX #29.
Home-page: https://github.com/mlodewijck/pyuegc
Author: Marc Lodewijck
Author-email: mlodewijck@gmail.com
License: MIT
Project-URL: Bug Reports, https://github.com/mlodewijck/pyuegc/issues
Project-URL: Source, https://github.com/mlodewijck/pyuegc/
Keywords: Unicode,Unicode grapheme clusters,extended grapheme clusters,EGC,grapheme clusters,graphemes,segmentation
Classifier: Intended Audience :: Developers
Classifier: License :: OSI Approved :: MIT License
Classifier: Programming Language :: Python :: 3.8
Classifier: Programming Language :: Python :: 3.9
Classifier: Programming Language :: Python :: 3.10
Classifier: Programming Language :: Python :: 3.11
Classifier: Programming Language :: Python :: 3.12
Classifier: Programming Language :: Python :: 3.13
Classifier: Topic :: Software Development
Classifier: Topic :: Software Development :: Internationalization
Classifier: Topic :: Software Development :: Localization
Classifier: Topic :: Software Development :: Libraries :: Python Modules
Classifier: Topic :: Text Processing
Classifier: Topic :: Utilities
Requires-Python: >=3.8
License-File: LICENSE
Dynamic: author
Dynamic: author-email
Dynamic: classifier
Dynamic: description
Dynamic: description-content-type
Dynamic: home-page
Dynamic: keywords
Dynamic: license
Dynamic: project-url
Dynamic: requires-python
Dynamic: summary
